.gitignore
HISTORY.rst
README.rst
setup.py
cmsplugin_googleform/__init__.py
cmsplugin_googleform/cms_plugins.py
cmsplugin_googleform/models.py
cmsplugin_googleform.egg-info/PKG-INFO
cmsplugin_googleform.egg-info/SOURCES.txt
cmsplugin_googleform.egg-info/dependency_links.txt
cmsplugin_googleform.egg-info/not-zip-safe
cmsplugin_googleform.egg-info/requires.txt
cmsplugin_googleform.egg-info/top_level.txt
cmsplugin_googleform/fixtures/README.txt
cmsplugin_googleform/fixtures/googleform.json
cmsplugin_googleform/migrations/0001_initial.py
cmsplugin_googleform/migrations/0002_add_dimensions.py
cmsplugin_googleform/migrations/__init__.py
cmsplugin_googleform/templates/cms/plugins/googleform/googleform.html