Metadata-Version: 1.1
Name: cmsplugin-googleform
Version: 0.1
Summary: Django CMS Plugin for Google Forms
Home-page: https://github.com/benliles/cmsplugin-googleform
Author: Corbin Fanning
Author-email: corbinfanning@gmail.com
License: UNKNOWN
Keywords: django cms plugin google forms docs
Platform: UNKNOWN
Classifier: Framework :: Django
Classifier: Development Status :: 4 - Beta
Classifier: Programming Language :: Python
Classifier: Topic :: Internet :: WWW/HTTP
Classifier: Topic :: Software Development :: Libraries :: Python Modules
Classifier: License :: OSI Approved :: Apache Software License
